typesafe_parmap/__init__.py
typesafe_parmap/named_thunk.py
typesafe_parmap/parmap.py
typesafe_parmap/parmap_timeout.py
typesafe_parmap/parmap_timeout_n.py
typesafe_parmap/py.typed
typesafe_parmap-1.0.7.dist-info/WHEEL
typesafe_parmap-1.0.7.dist-info/LICENSE
typesafe_parmap-1.0.7.dist-info/METADATA
typesafe_parmap-1.0.7.dist-info/RECORD
